MANIFEST.in
README.rst
setup.cfg
setup.py
unchaindjango/__init__.py
unchaindjango/data.py
unchaindjango/story.py
unchaindjango.egg-info/PKG-INFO
unchaindjango.egg-info/SOURCES.txt
unchaindjango.egg-info/dependency_links.txt
unchaindjango.egg-info/entry_points.txt
unchaindjango.egg-info/requires.txt
unchaindjango.egg-info/top_level.txt
unchaindjango/first_steps/README.rst
unchaindjango/first_steps/__init__.py