Metadata-Version: 1.1
Name: unchaindjango
Version: 0.0.5
Summary: Unchain Django - PySchool
Home-page: http://pyschool.github.io
Author: Sophilabs
Author-email: UNKNOWN
License: MIT
Download-URL: https://github.com/sophilabs/unchaindjango
Platform: UNKNOWN
Classifier: Development Status :: 5 - Production/Stable
Classifier: Intended Audience :: Developers
Classifier: Natural Language :: English
Classifier: License :: OSI Approved :: MIT License
Classifier: Programming Language :: Python
Classifier: Programming Language :: Python :: 3
Classifier: Programming Language :: Python :: 3.3
Classifier: Programming Language :: Python :: 3.4
Classifier: Environment :: Console
